awsutils/__init__.py
awsutils/services/__init__.py
awsutils/services/event_bridge.py
awsutils/services/lambda_types.py
awsutils/services/s3_client.py
awsutils/services/validate.py
learncloudops_utils-1.0.2.dist-info/LICENSE
learncloudops_utils-1.0.2.dist-info/METADATA
learncloudops_utils-1.0.2.dist-info/WHEEL
learncloudops_utils-1.0.2.dist-info/top_level.txt
learncloudops_utils-1.0.2.dist-info/RECORD
