Metadata-Version: 2.1
Name: learncloudops-utils
Version: 1.0.2
Summary: Useful OO abstractions for building aws cloud apps in Python
Home-page: https://github.com/learncloudops/awsutils
Author: learncloudops.com
License: UNKNOWN
Platform: UNKNOWN
Classifier: License :: OSI Approved :: MIT License
Classifier: Programming Language :: Python :: 3
Classifier: Programming Language :: Python :: 3.8
License-File: LICENSE
Requires-Dist: boto3
